grapnel/__init__.py
grapnel/_hook.py
grapnel/_hook_data.py
grapnel-0.2.0.dist-info/LICENSE
grapnel-0.2.0.dist-info/WHEEL
grapnel-0.2.0.dist-info/METADATA
grapnel-0.2.0.dist-info/RECORD
