Metadata-Version: 2.1
Name: grapnel
Version: 0.2.0
Summary: Add hooks to your python classes.
Author: artPlusPlus
Author-email: artPlusPlus@users.noreply.github.com
Requires-Python: >=3.7,<4.0
Classifier: Programming Language :: Python :: 3
Classifier: Programming Language :: Python :: 3.7
